{"season": "2004-2005", "league": "nba", "stadium": "Bradley Center", "time": "19:00:00", "code": "200411100MIL", "type": "Season", "away": {"scores": {"3": "18", "T": "100", "4": "20", "2": "32", "1": "30"}, "totals": {"FIC": 72.875, "pace": 90.3, "TSA": 99.24, "DRB": 29.0, "ORtg": 110.8, "eFG%": 0.4722222222222222, "2PAr": 0.8666666666666667, "DRtg": 113.0, "3PAr": 0.13333333333333333, "BLK%": 5.3, "FT%": 0.7142857142857143, "AST/TOV": 2.5, "DRBr": 0.6590909090909091, "3P": 5.0, "STL%": 7.8, "FG%": 0.4444444444444444, "DRB%": 74.4, "2P": 35.0, "HOB": 1.625, "TOV%": 9.2, "USG%": 100.0, "+/-": -2.0, "FTAr": 0.23333333333333334, "PF": 27.0, "TRB": 44.0, "STL/TOV": 0.7, "AST%": 62.5, "TRB%": 51.2, "2PA": 78.0, "ORB": 15.0, "ORB%": 31.9, "FT": 15.0, "FGA": 90.0, "ORBr": 0.3409090909090909, "FT/FGA": 0.16666666666666666, "TOV": 10.0, "BLK": 3.0, "MP": 240.0, "3P%": 0.4166666666666667, "2P%": 0.44871794871794873, "3PA": 12.0, "FTr": 0.233, "FTA": 21.0, "AST": 25.0, "PTS": 100.0, "FG": 40.0, "STL": 7.0, "TS%": 0.5038291011688836}, "players": {"Primoz Brezec": {"FIC": 11.25, "TSA": 17.76, "DRB": 1.0, "ORtg": 131.0, "eFG%": 0.5, "2PAr": 1.0, "DRtg": 117.0, "3PAr": 0.0, "BLK%": 5.0, "TS%": 0.563063063063063, "AST/TOV": null, "DRBr": 0.16666666666666666, "3P": 0.0, "STL%": 0.0, "FG%": 0.5, "DRB%": 3.6, "2P": 8.0, "HOB": 0.2, "TOV%": 0.0, "USG%": 23.0, "+/-": -9.0, "FTAr": 0.25, "PF": 6.0, "TRB": 6.0, "name": "Primoz Brezec", "PTS": 20.0, "AST%": 0.0, "college": "", "TRB%": 9.8, "2PA": 16.0, "ORB": 5.0, "ORB%": 15.0, "FT": 4.0, "FGA": 16.0, "ORBr": 0.8333333333333334, "FT/FGA": 0.25, "experience": 3, "TOV": 0.0, "height": 2.194586686174104, "BLK": 2.0, "MP": 34.0, "3P%": null, "2P%": 0.5, "3PA": 0.0, "position": "C", "FTr": 0.25, "FTA": 4.0, "number": "7", "AST": 0.0, "weight": "252", "birth_date": "1979-10-02", "STL/TOV": null, "FG": 8.0, "STL": 0.0, "FT%": 1.0}, "Jason Hart": {"FIC": 24.5, "TSA": 11.52, "DRB": 4.0, "ORtg": 157.0, "eFG%": 0.75, "2PAr": 1.0, "DRtg": 107.0, "3PAr": 0.0, "BLK%": 0.0, "TS%": 0.8246527777777778, "AST/TOV": 6.0, "DRBr": 1.0, "3P": 0.0, "STL%": 4.8, "FG%": 0.75, "DRB%": 14.9, "2P": 6.0, "HOB": 0.45, "TOV%": 14.8, "USG%": 18.0, "+/-": -10.0, "FTAr": 1.0, "PF": 3.0, "TRB": 4.0, "name": "Jason Hart", "PTS": 19.0, "AST%": 55.8, "college": "Syracuse University", "TRB%": 6.8, "2PA": 8.0, "ORB": 0.0, "ORB%": 0.0, "FT": 7.0, "FGA": 8.0, "ORBr": 0.0, "FT/FGA": 0.875, "experience": 3, "TOV": 2.0, "height": 1.9202633504023408, "BLK": 0.0, "MP": 33.0, "3P%": null, "2P%": 0.75, "3PA": 0.0, "position": "PG", "FTr": 1.0, "FTA": 8.0, "number": "1", "AST": 12.0, "weight": "185", "birth_date": "1978-04-29", "STL/TOV": 1.5, "FG": 6.0, "STL": 3.0, "FT%": 0.875}, "Emeka Okafor": {"FIC": 9.25, "TSA": 11.0, "DRB": 8.0, "ORtg": 78.0, "eFG%": 0.36363636363636365, "2PAr": 1.0, "DRtg": 112.0, "3PAr": 0.0, "BLK%": 0.0, "TS%": 0.36363636363636365, "AST/TOV": 0.75, "DRBr": 0.6153846153846154, "3P": 0.0, "STL%": 1.3, "FG%": 0.36363636363636365, "DRB%": 24.0, "2P": 4.0, "HOB": 0.175, "TOV%": 26.7, "USG%": 16.1, "+/-": -4.0, "FTAr": 0.0, "PF": 3.0, "TRB": 13.0, "name": "Emeka Okafor", "PTS": 8.0, "AST%": 9.9, "college": "University of Connecticut", "TRB%": 17.7, "2PA": 11.0, "ORB": 5.0, "ORB%": 12.5, "FT": 0.0, "FGA": 11.0, "ORBr": 0.38461538461538464, "FT/FGA": 0.0, "experience": 0, "TOV": 4.0, "height": 1.8593026091197267, "BLK": 0.0, "MP": 41.0, "3P%": null, "2P%": 0.36363636363636365, "3PA": 0.0, "position": "PF", "FTr": 0.0, "FTA": 0.0, "number": "50", "AST": 3.0, "weight": "252", "birth_date": "1982-09-28", "STL/TOV": 0.25, "FG": 4.0, "STL": 1.0, "FT%": null}, "Steve Smith": {"FIC": 3.0, "TSA": 10.88, "DRB": 3.0, "ORtg": 83.0, "eFG%": 0.25, "2PAr": 0.5, "DRtg": 118.0, "3PAr": 0.5, "BLK%": 0.0, "TS%": 0.3216911764705882, "AST/TOV": 4.0, "DRBr": 1.0, "3P": 1.0, "STL%": 0.0, "FG%": 0.2, "DRB%": 11.9, "2P": 1.0, "HOB": 0.15, "TOV%": 8.4, "USG%": 16.8, "+/-": 5.0, "FTAr": 0.2, "PF": 2.0, "TRB": 3.0, "name": "Steve Smith", "PTS": 7.0, "AST%": 16.8, "college": "Michigan State University", "TRB%": 5.4, "2PA": 5.0, "ORB": 0.0, "ORB%": 0.0, "FT": 2.0, "FGA": 10.0, "ORBr": 0.0, "FT/FGA": 0.2, "experience": 13, "TOV": 1.0, "height": 2.042184832967569, "BLK": 0.0, "MP": 31.0, "3P%": 0.2, "2P%": 0.2, "3PA": 5.0, "position": "SG", "FTr": 0.2, "FTA": 2.0, "number": "8", "AST": 4.0, "weight": "200", "birth_date": "1969-03-31", "STL/TOV": 0.0, "FG": 2.0, "STL": 0.0, "FT%": 1.0}, "Gerald Wallace": {"FIC": 8.0, "TSA": 14.0, "DRB": 6.0, "ORtg": 89.0, "eFG%": 0.42857142857142855, "2PAr": 1.0, "DRtg": 108.0, "3PAr": 0.0, "BLK%": 0.0, "TS%": 0.42857142857142855, "AST/TOV": 1.5, "DRBr": 0.8571428571428571, "3P": 0.0, "STL%": 3.2, "FG%": 0.42857142857142855, "DRB%": 22.4, "2P": 6.0, "HOB": 0.225, "TOV%": 12.5, "USG%": 21.3, "+/-": 0.0, "FTAr": 0.0, "PF": 4.0, "TRB": 7.0, "name": "Gerald Wallace", "PTS": 12.0, "AST%": 14.0, "college": "University of Alabama", "TRB%": 11.8, "2PA": 14.0, "ORB": 1.0, "ORB%": 3.1, "FT": 0.0, "FGA": 14.0, "ORBr": 0.14285714285714285, "FT/FGA": 0.0, "experience": 3, "TOV": 2.0, "height": 2.042184832967569, "BLK": 0.0, "MP": 33.0, "3P%": null, "2P%": 0.42857142857142855, "3PA": 0.0, "position": "SF", "FTr": 0.0, "FTA": 0.0, "number": "3", "AST": 3.0, "weight": "215", "birth_date": "1982-07-23", "STL/TOV": 1.0, "FG": 6.0, "STL": 2.0, "FT%": null}, "Eddie House": {"FIC": 7.75, "TSA": 16.0, "DRB": 3.0, "ORtg": 101.0, "eFG%": 0.46875, "2PAr": 0.625, "DRtg": 114.0, "3PAr": 0.375, "BLK%": 0.0, "TS%": 0.46875, "AST/TOV": 3.0, "DRBr": 1.0, "3P": 3.0, "STL%": 1.9, "FG%": 0.375, "DRB%": 13.2, "2P": 3.0, "HOB": 0.225, "TOV%": 5.9, "USG%": 26.7, "+/-": -1.0, "FTAr": 0.0, "PF": 1.0, "TRB": 3.0, "name": "Eddie House", "PTS": 15.0, "AST%": 17.3, "college": "Arizona State University", "TRB%": 6.0, "2PA": 10.0, "ORB": 0.0, "ORB%": 0.0, "FT": 0.0, "FGA": 16.0, "ORBr": 0.0, "FT/FGA": 0.0, "experience": 4, "TOV": 1.0, "height": 1.8593026091197267, "BLK": 0.0, "MP": 28.0, "3P%": 0.5, "2P%": 0.3, "3PA": 6.0, "position": "SG", "FTr": 0.0, "FTA": 0.0, "number": "5", "AST": 3.0, "weight": "180", "birth_date": "1978-05-14", "STL/TOV": 1.0, "FG": 6.0, "STL": 1.0, "FT%": null}, "Jason Kapono": {"FIC": 3.5, "TSA": 9.0, "DRB": 1.0, "ORtg": 128.0, "eFG%": 0.6111111111111112, "2PAr": 0.8888888888888888, "DRtg": 119.0, "3PAr": 0.1111111111111111, "BLK%": 0.0, "TS%": 0.6111111111111112, "AST/TOV": null, "DRBr": 0.5, "3P": 1.0, "STL%": 0.0, "FG%": 0.5555555555555556, "DRB%": 6.5, "2P": 4.0, "HOB": 0.125, "TOV%": 0.0, "USG%": 20.8, "+/-": 1.0, "FTAr": 0.0, "PF": 5.0, "TRB": 2.0, "name": "Jason Kapono", "PTS": 11.0, "AST%": 0.0, "college": "University of California, Los Angeles", "TRB%": 5.9, "2PA": 8.0, "ORB": 1.0, "ORB%": 5.4, "FT": 0.0, "FGA": 9.0, "ORBr": 0.5, "FT/FGA": 0.0, "experience": 1, "TOV": 0.0, "height": 2.0726652036088757, "BLK": 0.0, "MP": 19.0, "3P%": 1.0, "2P%": 0.5, "3PA": 1.0, "position": "SF", "FTr": 0.0, "FTA": 0.0, "number": "24", "AST": 0.0, "weight": "213", "birth_date": "1981-02-04", "STL/TOV": null, "FG": 5.0, "STL": 0.0, "FT%": null}, "Bernard Robinson": {"FIC": 0.0, "TSA": 0.0, "DRB": 0.0, "ORtg": null, "eFG%": null, "2PAr": null, "DRtg": 122.0, "3PAr": null, "BLK%": 0.0, "TS%": null, "AST/TOV": null, "DRBr": null, "3P": 0.0, "STL%": 0.0, "FG%": null, "DRB%": 0.0, "2P": 0.0, "HOB": 0.0, "TOV%": null, "USG%": 0.0, "+/-": -3.0, "FTAr": null, "PF": 0.0, "TRB": 0.0, "name": "Bernard Robinson", "PTS": 0.0, "AST%": 0.0, "college": "University of Michigan", "TRB%": 0.0, "2PA": 0.0, "ORB": 0.0, "ORB%": 0.0, "FT": 0.0, "FGA": 0.0, "ORBr": null, "FT/FGA": null, "experience": 0, "TOV": 0.0, "height": 2.0117044623262617, "BLK": 0.0, "MP": 3.0, "3P%": null, "2P%": null, "3PA": 0.0, "position": "SG", "FTr": null, "FTA": 0.0, "number": "21", "AST": 0.0, "weight": "210", "birth_date": "1980-12-26", "STL/TOV": null, "FG": 0.0, "STL": 0.0, "FT%": null}, "Jahidi White": {"FIC": 5.625, "TSA": 9.08, "DRB": 3.0, "ORtg": 104.0, "eFG%": 0.5, "2PAr": 1.0, "DRtg": 112.0, "3PAr": 0.0, "BLK%": 4.7, "TS%": 0.44052863436123346, "AST/TOV": null, "DRBr": 0.5, "3P": 0.0, "STL%": 0.0, "FG%": 0.5, "DRB%": 20.5, "2P": 3.0, "HOB": 0.075, "TOV%": 0.0, "USG%": 22.2, "+/-": 11.0, "FTAr": 1.1666666666666667, "PF": 3.0, "TRB": 6.0, "name": "Jahidi White", "PTS": 8.0, "AST%": 0.0, "college": "Georgetown University", "TRB%": 18.6, "2PA": 6.0, "ORB": 3.0, "ORB%": 17.0, "FT": 2.0, "FGA": 6.0, "ORBr": 0.5, "FT/FGA": 0.3333333333333333, "experience": 6, "TOV": 0.0, "height": 2.103145574250183, "BLK": 1.0, "MP": 18.0, "3P%": null, "2P%": 0.5, "3PA": 0.0, "position": "C", "FTr": 1.167, "FTA": 7.0, "number": "55", "AST": 0.0, "weight": "290", "birth_date": "1976-02-19", "STL/TOV": null, "FG": 3.0, "STL": 0.0, "FT%": 0.2857142857142857}}, "name": "Charlotte Bobcats"}, "date": "2004-11-10", "attendance": 17029, "officials": ["Gary Benson", "Blane Reichelt", "Greg Willard"], "home": {"scores": {"3": "20", "T": "102", "4": "28", "2": "33", "1": "21"}, "totals": {"FIC": 73.625, "pace": 90.3, "TSA": 89.92, "DRB": 32.0, "ORtg": 113.0, "eFG%": 0.47183098591549294, "2PAr": 0.8028169014084507, "DRtg": 110.8, "3PAr": 0.19718309859154928, "BLK%": 7.7, "FT%": 0.813953488372093, "AST/TOV": 1.5833333333333333, "DRBr": 0.7619047619047619, "3P": 5.0, "STL%": 5.5, "FG%": 0.43661971830985913, "DRB%": 68.1, "2P": 26.0, "HOB": 1.6129032258064515, "TOV%": 11.8, "USG%": 100.0, "+/-": 2.0, "FTAr": 0.6056338028169014, "PF": 22.0, "TRB": 42.0, "STL/TOV": 0.4166666666666667, "AST%": 61.3, "TRB%": 48.8, "2PA": 57.0, "ORB": 10.0, "ORB%": 25.6, "FT": 35.0, "FGA": 71.0, "ORBr": 0.23809523809523808, "FT/FGA": 0.49295774647887325, "TOV": 12.0, "BLK": 6.0, "MP": 240.0, "3P%": 0.35714285714285715, "2P%": 0.45614035087719296, "3PA": 14.0, "FTr": 0.606, "FTA": 43.0, "AST": 19.0, "PTS": 102.0, "FG": 31.0, "STL": 5.0, "TS%": 0.567170818505338}, "players": {"Toni Kukoc": {"FIC": 2.75, "TSA": 1.0, "DRB": 2.0, "ORtg": 103.0, "eFG%": 0.0, "2PAr": 1.0, "DRtg": 112.0, "3PAr": 0.0, "BLK%": 0.0, "TS%": 0.0, "AST/TOV": null, "DRBr": 1.0, "3P": 0.0, "STL%": 0.0, "FG%": 0.0, "DRB%": 17.0, "2P": 0.0, "HOB": 0.0967741935483871, "TOV%": 0.0, "USG%": 3.9, "+/-": 1.0, "FTAr": 0.0, "PF": 2.0, "TRB": 2.0, "name": "Toni Kukoc", "PTS": 0.0, "AST%": 38.7, "college": "", "TRB%": 9.3, "2PA": 1.0, "ORB": 0.0, "ORB%": 0.0, "FT": 0.0, "FGA": 1.0, "ORBr": 0.0, "FT/FGA": 0.0, "experience": 11, "TOV": 0.0, "height": 1.8593026091197267, "BLK": 0.0, "MP": 12.0, "3P%": null, "2P%": 0.0, "3PA": 0.0, "position": "SF", "FTr": 0.0, "FTA": 0.0, "number": "7", "AST": 3.0, "weight": "192", "birth_date": "1968-09-18", "STL/TOV": null, "FG": 0.0, "STL": 0.0, "FT%": null}, "Mo Williams": {"FIC": 10.5, "TSA": 11.88, "DRB": 6.0, "ORtg": 82.0, "eFG%": 0.2727272727272727, "2PAr": 1.0, "DRtg": 109.0, "3PAr": 0.0, "BLK%": 3.8, "TS%": 0.33670033670033667, "AST/TOV": 2.5, "DRBr": 0.8571428571428571, "3P": 0.0, "STL%": 0.0, "FG%": 0.2727272727272727, "DRB%": 19.1, "2P": 3.0, "HOB": 0.41935483870967744, "TOV%": 25.2, "USG%": 23.4, "+/-": 7.0, "FTAr": 0.18181818181818182, "PF": 4.0, "TRB": 7.0, "name": "Mo Williams", "PTS": 8.0, "AST%": 56.6, "college": "University of Alabama", "TRB%": 12.2, "2PA": 11.0, "ORB": 1.0, "ORB%": 3.8, "FT": 2.0, "FGA": 11.0, "ORBr": 0.14285714285714285, "FT/FGA": 0.18181818181818182, "experience": 1, "TOV": 4.0, "height": 1.8593026091197267, "BLK": 2.0, "MP": 32.0, "3P%": null, "2P%": 0.2727272727272727, "3PA": 0.0, "position": "PG", "FTr": 0.182, "FTA": 2.0, "number": "25", "AST": 10.0, "weight": "198", "birth_date": "1982-12-19", "STL/TOV": 0.0, "FG": 3.0, "STL": 0.0, "FT%": 1.0}, "Michael Redd": {"FIC": 15.0, "TSA": 21.28, "DRB": 8.0, "ORtg": 120.0, "eFG%": 0.46875, "2PAr": 0.75, "DRtg": 107.0, "3PAr": 0.25, "BLK%": 0.0, "TS%": 0.6109022556390977, "AST/TOV": 0.5, "DRBr": 1.0, "3P": 1.0, "STL%": 2.5, "FG%": 0.4375, "DRB%": 19.5, "2P": 6.0, "HOB": 0.25806451612903225, "TOV%": 8.6, "USG%": 26.1, "+/-": 4.0, "FTAr": 0.75, "PF": 3.0, "TRB": 8.0, "name": "Michael Redd", "PTS": 26.0, "AST%": 5.0, "college": "Ohio State University", "TRB%": 10.6, "2PA": 12.0, "ORB": 0.0, "ORB%": 0.0, "FT": 11.0, "FGA": 16.0, "ORBr": 0.0, "FT/FGA": 0.6875, "experience": 4, "TOV": 2.0, "height": 2.0117044623262617, "BLK": 0.0, "MP": 42.0, "3P%": 0.25, "2P%": 0.5, "3PA": 4.0, "position": "SG", "FTr": 0.75, "FTA": 12.0, "number": "22", "AST": 1.0, "weight": "220", "birth_date": "1979-08-24", "STL/TOV": 1.0, "FG": 7.0, "STL": 2.0, "FT%": 0.9166666666666666}, "Desmond Mason": {"FIC": 22.75, "TSA": 19.04, "DRB": 3.0, "ORtg": 176.0, "eFG%": 0.6666666666666666, "2PAr": 1.0, "DRtg": 112.0, "3PAr": 0.0, "BLK%": 1.8, "TS%": 0.8140756302521008, "AST/TOV": null, "DRBr": 0.75, "3P": 0.0, "STL%": 1.5, "FG%": 0.6666666666666666, "DRB%": 8.8, "2P": 8.0, "HOB": 0.3225806451612903, "TOV%": 0.0, "USG%": 25.6, "+/-": 4.0, "FTAr": 1.3333333333333333, "PF": 1.0, "TRB": 4.0, "name": "Desmond Mason", "PTS": 31.0, "AST%": 13.7, "college": "Oklahoma State University", "TRB%": 6.4, "2PA": 12.0, "ORB": 1.0, "ORB%": 3.5, "FT": 15.0, "FGA": 12.0, "ORBr": 0.25, "FT/FGA": 1.25, "experience": 4, "TOV": 0.0, "height": 2.042184832967569, "BLK": 1.0, "MP": 35.0, "3P%": null, "2P%": 0.6666666666666666, "3PA": 0.0, "position": "SF", "FTr": 1.333, "FTA": 16.0, "number": "24", "AST": 2.0, "weight": "224", "birth_date": "1977-10-11", "STL/TOV": null, "FG": 8.0, "STL": 1.0, "FT%": 0.9375}, "Keith Van Horn": {"FIC": 8.75, "TSA": 19.76, "DRB": 3.0, "ORtg": 111.0, "eFG%": 0.5277777777777778, "2PAr": 0.5, "DRtg": 116.0, "3PAr": 0.5, "BLK%": 0.0, "TS%": 0.5819838056680161, "AST/TOV": 0.5, "DRBr": 0.75, "3P": 3.0, "STL%": 0.0, "FG%": 0.4444444444444444, "DRB%": 7.9, "2P": 5.0, "HOB": 0.2903225806451613, "TOV%": 9.2, "USG%": 26.3, "+/-": -1.0, "FTAr": 0.2222222222222222, "PF": 3.0, "TRB": 4.0, "name": "Keith Van Horn", "PTS": 23.0, "AST%": 5.8, "college": "University of Utah", "TRB%": 5.7, "2PA": 9.0, "ORB": 1.0, "ORB%": 3.2, "FT": 4.0, "FGA": 18.0, "ORBr": 0.25, "FT/FGA": 0.2222222222222222, "experience": 7, "TOV": 2.0, "height": 1.8593026091197267, "BLK": 0.0, "MP": 39.0, "3P%": 0.3333333333333333, "2P%": 0.5555555555555556, "3PA": 9.0, "position": "SF", "FTr": 0.222, "FTA": 4.0, "number": "44", "AST": 1.0, "weight": "220", "birth_date": "1975-10-23", "STL/TOV": 0.0, "FG": 8.0, "STL": 0.0, "FT%": 1.0}, "Daniel Santiago": {"FIC": 0.0, "TSA": 1.88, "DRB": 0.0, "ORtg": 63.0, "eFG%": 0.0, "2PAr": 1.0, "DRtg": 116.0, "3PAr": 0.0, "BLK%": 4.7, "TS%": 0.26595744680851063, "AST/TOV": null, "DRBr": null, "3P": 0.0, "STL%": 0.0, "FG%": 0.0, "DRB%": 0.0, "2P": 0.0, "HOB": 0.0, "TOV%": 0.0, "USG%": 6.8, "+/-": -7.0, "FTAr": 2.0, "PF": 1.0, "TRB": 0.0, "name": "Daniel Santiago", "PTS": 1.0, "AST%": 0.0, "college": "Saint Vincent College", "TRB%": 0.0, "2PA": 1.0, "ORB": 0.0, "ORB%": 0.0, "FT": 1.0, "FGA": 1.0, "ORBr": null, "FT/FGA": 1.0, "experience": 3, "TOV": 0.0, "height": 2.1641063155327966, "BLK": 1.0, "MP": 13.0, "3P%": null, "2P%": 0.0, "3PA": 0.0, "position": "C", "FTr": 2.0, "FTA": 2.0, "number": "15", "AST": 0.0, "weight": "256", "birth_date": "1976-06-24", "STL/TOV": null, "FG": 0.0, "STL": 0.0, "FT%": 0.5}, "Joe Smith": {"FIC": 7.125, "TSA": 5.44, "DRB": 7.0, "ORtg": 94.0, "eFG%": 0.6, "2PAr": 1.0, "DRtg": 107.0, "3PAr": 0.0, "BLK%": 0.0, "TS%": 0.6433823529411764, "AST/TOV": 0.0, "DRBr": 0.7, "3P": 0.0, "STL%": 1.7, "FG%": 0.6, "DRB%": 22.3, "2P": 3.0, "HOB": 0.0967741935483871, "TOV%": 35.5, "USG%": 12.4, "+/-": 1.0, "FTAr": 0.2, "PF": 4.0, "TRB": 10.0, "name": "Joe Smith", "PTS": 7.0, "AST%": 0.0, "college": "University of Maryland", "TRB%": 17.4, "2PA": 5.0, "ORB": 3.0, "ORB%": 11.5, "FT": 1.0, "FGA": 5.0, "ORBr": 0.3, "FT/FGA": 0.2, "experience": 9, "TOV": 3.0, "height": 1.8593026091197267, "BLK": 0.0, "MP": 32.0, "3P%": null, "2P%": 0.6, "3PA": 0.0, "position": "PF", "FTr": 0.2, "FTA": 1.0, "number": "8", "AST": 0.0, "weight": "225", "birth_date": "1975-07-26", "STL/TOV": 0.3333333333333333, "FG": 3.0, "STL": 1.0, "FT%": 1.0}, "Erick Strickland": {"FIC": 5.0, "TSA": 4.0, "DRB": 2.0, "ORtg": 107.0, "eFG%": 0.625, "2PAr": 0.75, "DRtg": 109.0, "3PAr": 0.25, "BLK%": 0.0, "TS%": 0.625, "AST/TOV": 2.0, "DRBr": 1.0, "3P": 1.0, "STL%": 3.0, "FG%": 0.5, "DRB%": 11.3, "2P": 1.0, "HOB": 0.12903225806451613, "TOV%": 20.0, "USG%": 13.1, "+/-": -4.0, "FTAr": 0.0, "PF": 1.0, "TRB": 2.0, "name": "Erick Strickland", "PTS": 5.0, "AST%": 20.8, "college": "University of Nebraska", "TRB%": 6.2, "2PA": 3.0, "ORB": 0.0, "ORB%": 0.0, "FT": 0.0, "FGA": 4.0, "ORBr": 0.0, "FT/FGA": 0.0, "experience": 8, "TOV": 1.0, "height": 1.9202633504023408, "BLK": 0.0, "MP": 18.0, "3P%": 1.0, "2P%": 0.3333333333333333, "3PA": 1.0, "position": "SG", "FTr": 0.0, "FTA": 0.0, "number": "20", "AST": 2.0, "weight": "210", "birth_date": "1973-11-25", "STL/TOV": 1.0, "FG": 2.0, "STL": 1.0, "FT%": null}, "Dan Gadzuric": {"FIC": 1.75, "TSA": 5.640000000000001, "DRB": 1.0, "ORtg": 66.0, "eFG%": 0.0, "2PAr": 1.0, "DRtg": 111.0, "3PAr": 0.0, "BLK%": 7.2, "TS%": 0.08865248226950354, "AST/TOV": null, "DRBr": 0.2, "3P": 0.0, "STL%": 0.0, "FG%": 0.0, "DRB%": 6.0, "2P": 0.0, "HOB": 0.0, "TOV%": 0.0, "USG%": 15.6, "+/-": 5.0, "FTAr": 2.0, "PF": 3.0, "TRB": 5.0, "name": "Dan Gadzuric", "PTS": 1.0, "AST%": 0.0, "college": "University of California, Los Angeles", "TRB%": 16.4, "2PA": 3.0, "ORB": 4.0, "ORB%": 29.0, "FT": 1.0, "FGA": 3.0, "ORBr": 0.8, "FT/FGA": 0.3333333333333333, "experience": 2, "TOV": 0.0, "height": 1.8623506461838577, "BLK": 2.0, "MP": 17.0, "3P%": null, "2P%": 0.0, "3PA": 0.0, "position": "C", "FTr": 2.0, "FTA": 6.0, "number": "50", "AST": 0.0, "weight": "240", "birth_date": "1978-02-02", "STL/TOV": null, "FG": 0.0, "STL": 0.0, "FT%": 0.16666666666666666}}, "name": "Milwaukee Bucks"}, "country": "United States"}